func_router
