Metadata-Version: 2.1
Name: func_router
Version: 0.0.3
Summary: method overload dispatcher.
Home-page: https://github.com/coderelease
Author: Yang Xiang
Author-email: btk@qq.com
License: MIT
Keywords: func_router
Classifier: Intended Audience :: Developers
Classifier: License :: OSI Approved :: MIT License
Classifier: Natural Language :: English
Classifier: Programming Language :: Python :: 3.8
Classifier: Programming Language :: Python :: 3.9
Classifier: Programming Language :: Python :: 3.10
Requires-Python: >=3.8.0
License-File: LICENSE
Requires-Dist: setuptools
